README.md
setup.py
ansibleawx/__init__.py
ansibleawx/api.py
ansibleawx/decorators.py
ansibleawx/exceptions.py
ansibleawx_client.egg-info/PKG-INFO
ansibleawx_client.egg-info/SOURCES.txt
ansibleawx_client.egg-info/dependency_links.txt
ansibleawx_client.egg-info/requires.txt
ansibleawx_client.egg-info/top_level.txt
tests/__init__.py
tests/conftest.py
tests/test_job.py