Metadata-Version: 2.1
Name: ansibleawx-client
Version: 0.1.1
Summary: Ansible AWX Client
Home-page: https://github.com/mdiniz97/AnsibleAWX-Client/
Author: Marcos Diniz
Author-email: marcosdinizpaulo@gmail.com
License: MIT
Platform: UNKNOWN
Classifier: Environment :: Web Environment
Classifier: Intended Audience :: Developers
Classifier: License :: OSI Approved :: MIT License
Classifier: Operating System :: OS Independent
Classifier: Programming Language :: Python
Classifier: Topic :: Internet :: WWW/HTTP :: Dynamic Content
Classifier: Topic :: Software Development :: Libraries :: Python Modules
